<?xml version="1.0" encoding="UTF-8"?>
<Lib nameU="3D Network Diagram Shapes"><Elem NameU="Oblique connector" Name="Connecteur oblique"/><Elem NameU="Oblique connector 2" Name="Connecteur oblique 2"/><Elem NameU="Flexi connector" Name="Connecteur flexible"/><Elem NameU="Line connector" Name="Connecteur de ligne"/><Elem NameU="1U Server" Name="Serveur 1U"/><Elem NameU="1U Server Stack" Name="Serveur empilé 1U"/><Elem NameU="2U Server" Name="Serveur 2U"/><Elem NameU="2U Server Stack" Name="Serveur empilé 2U"/><Elem NameU="Switch" Name="Commutateur"/><Elem NameU="Switch Pool" Name="Commutateur empilable"/><Elem NameU="Modem Pool" Name="Modem empilé"/><Elem NameU="Terminal Server" Name="Serveur de terminaux"/><Elem NameU="PC" Name="PC"/><Elem NameU="PC 2" Name="PC 2"/><Elem NameU="Laptop" Name="Portatif"/><Elem NameU="Server" Name="Serveur"/><Elem NameU="Server 2" Name="Serveur 2"/><Elem NameU="Computer Lab" Name="Laboratoire informatique"/><Elem NameU="Computer Lab 2" Name="Laboratoire informatique 2"/><Elem NameU="Switch Symbol" Name="Symbole de commutateur"/><Elem NameU="ISDN Switch" Name="Commutateur ISDN"/><Elem NameU="Router" Name="Routeur"/><Elem NameU="CDDI-FDDI concentrator" Name="CDDI-FDDI concentrateur"/><Elem NameU="Bridge" Name="Pont"/><Elem NameU="Hub" Name="Hub"/><Elem NameU="Gateway" Name="Passerelle"/><Elem NameU="WAN" Name="WAN"/><Elem NameU="Host" Name="Hôte"/><Elem NameU="Office" Name="Bureau"/><Elem NameU="Firewall" Name="Pare-feu"/><Elem NameU="Ring" Name="Anneau"/><Elem NameU="Internet" Name="Internet"/><Elem NameU="Internet Cloud" Name="Cloud Internet"/><Elem NameU="Hacker" Name="Pirate"/><Elem NameU="No hackers" Name="Pas de pirates"/><Elem NameU="Network security system" Name="Système de sécurité de réseau"/><Elem NameU="Network Planning" Name="Planification du réseau"/><Elem NameU="Curved Connector" Name="Connecteur courbe"/><Elem NameU="Token Ring" Name="Token Ring"/><Elem NameU="Arrow 1" Name="Flèche 1"/><Elem NameU="Arrow 2" Name="Flèche 2"/><Elem NameU="Arrow 3" Name="Flèche 3"/><Elem NameU="Arrow 4" Name="Flèche 4"/><Elem NameU="Center drag circle" Name="Centre glisser cercle"/><Elem NameU="Center drag circle 2" Name="Centre glisser cercle 2"/></Lib>