<?xml version="1.0" encoding="utf-8"?><Lib nameU="IDEF0"><Elem NameU="Process box" Name="Bloc de processus"/><Elem NameU="Title block" Name="Bloc de titre"/><Elem NameU="N-type line" Name="Ligne en N"/><Elem NameU="Text block" Name="Bloc de texte"/><Elem NameU="Node" Name="Nœud"/><Elem NameU="1 legged connector" Name="Lien 1 branche"/><Elem NameU="IDEF0 connector" Name="Lien IDEF0"/><Elem NameU="Dynamic connector" Name="Lien dynamique"/><Elem NameU="Side text callout" Name="Légende-texte à côté"/></Lib>