<?xml version="1.0" encoding="UTF-8"?>
<Lib nameU="Shlaer-Mellor OOA"><Elem NameU="Class Box" Name="Boîte de classe"/><Elem NameU="Small Class Box" Name="Petite boîte de classe"/><Elem NameU="Published Operation" Name="Opération publiée"/><Elem NameU="Defering Operation" Name="Opération différente"/><Elem NameU="Logical Component" Name="Composant logique"/><Elem NameU="Conditional Parameter" Name="Paramètre conditionnel"/><Elem NameU="Basis Marker" Name="Marqueur simple"/><Elem NameU="Exception" Name="Exception"/><Elem NameU="Exception Handler" Name="Gestionnaire d'exception"/><Elem NameU="Parameter List" Name="Liste des paramètres"/><Elem NameU="Module" Name="Module"/><Elem NameU="Instance Data" Name="Données d'instance"/><Elem NameU="Foreign Module" Name="Module étranger"/></Lib>