<?xml version="1.0" encoding="UTF-8"?>
<Lib nameU="Terminals and Connectors"><Elem NameU="Male Contact" Name="Contact M"/><Elem NameU="Female Contact" Name="Contact F"/><Elem NameU="Male Contact 2" Name="Contact M 2"/><Elem NameU="Female Contact 2" Name="Contact F 2"/><Elem NameU="Adapter" Name="Adaptateur"/><Elem NameU="Cable terminal" Name="Cable terminal"/><Elem NameU="Circuit terminal" Name="Borne de circuit"/><Elem NameU="Terminal board" Name="Tablette à bornes"/><Elem NameU="Cable termination" Name="Connexion des câbles"/><Elem NameU="2-conductor jack" Name="Prise à 2 conducteurs"/><Elem NameU="2-conductor plug" Name="Fiche à 2 conducteurs"/><Elem NameU="Normalled jacks" Name="Prise normalisée"/><Elem NameU="Normalled jack" Name="Prises normalisées"/><Elem NameU="Coaxial outside conductor" Name="Conducteur coaxial extérieur"/><Elem NameU="Coaxial center conductor" Name="Conducteur central coaxial"/><Elem NameU="Large D connector" Name="Con.haute densité"/><Elem NameU="Small D connector" Name="Con.faible D"/><Elem NameU="C header connector" Name="Connecteur en-tête C"/><Elem NameU="Shielded jack/plug" Name="Prise blindée"/><Elem NameU="Coaxial jack/plug" Name="P./fiche coaxial"/><Elem NameU="F/M 2-conductor 1" Name="2 conducteur F/M 1"/><Elem NameU="F/M 2-conductor 2" Name="2 conducteur F/M 2"/><Elem NameU="F/M 2-conductor 3" Name="2 conducteur F/M 3"/><Elem NameU="F/M 3-conductor 1" Name="3 conducteur F/M 1"/><Elem NameU="F/M 3-conductor 2" Name="3 conducteur F/M 2"/><Elem NameU="F/M 3-conductor 3" Name="3 conducteur F/M 3"/><Elem NameU="F/M 3-conductor 4" Name="3 conducteur F/M 4"/><Elem NameU="F/M 3-conductor 5" Name="3 conducteur F/M 5"/><Elem NameU="Mated pair" Name="Paire accouplée"/><Elem NameU="3-conductor plug" Name="Fiche à 3 conducteurs"/><Elem NameU="3-conductor jack" Name="Prise à 3 conducteurs"/></Lib>