<?xml version="1.0" encoding="UTF-8"?>
<Lib NameU="Children's Day">
	<Elem NameU="0" Name="0"/>
	<Elem NameU="1" Name="1"/>
	<Elem NameU="2" Name="2"/>
	<Elem NameU="3" Name="3"/>
	<Elem NameU="4" Name="4"/>
	<Elem NameU="5" Name="5"/>
	<Elem NameU="6" Name="6"/>
	<Elem NameU="7" Name="7"/>
	<Elem NameU="8" Name="8"/>
	<Elem NameU="9" Name="9"/>
	<Elem NameU="Lollipop" Name="Lecca lecca"/>
	<Elem NameU="Kanto Cooking" Name="Cucina del Kanto"/>
	<Elem NameU="Bear" Name="Orso"/>
	<Elem NameU="Little Yellow Duck" Name="Piccola Papera Gialla"/>
	<Elem NameU="Toy" Name="Giocattolo"/>
	<Elem NameU="Alphabet Blocks" Name="Cubi con Alfabeto "/>
	<Elem NameU="Toy Boat" Name="Barca Giocattolo"/>
	<Elem NameU="Drum" Name="Batteria"/>
	<Elem NameU="Capsule" Name="Capsula"/>
	<Elem NameU="Gyro" Name="Gyro"/>
	<Elem NameU="Toy Car" Name="Macchina Giocattolo"/>
	<Elem NameU="Remote Control" Name="Telecomando"/>
	<Elem NameU="Holding a Aell" name="Tenendo un Aell"/>
	<Elem NameU="Puzzle" Name="Puzzle"/>
	<Elem NameU="Small Train" Name="Trenino"/>
	<Elem NameU="Holding a Bell" Name="Tenendo una Campana"/>
	<Elem NameU="Ball" Name="Palla"/>
	<Elem NameU="Rope" Name="Corda"/>
	<Elem NameU="Dominoes" Name="Domino"/>
	<Elem NameU="Walker" Name="Girello"/>
	<Elem NameU="Windmill" Name="Mulino"/>
	<Elem NameU="Carousel" Name="Giostra"/>
	<Elem NameU="Candy" Name="Caramella"/>
	<Elem NameU="Moon" Name="Luna"/>
	<Elem NameU="Horse" Name="Cavallo"/>
	<Elem NameU="Trojan" Name="Cavallo di Troia"/>
	<Elem NameU="Fish" Name="Pesce"/>
	<Elem NameU="Bucket and Shovel" Name="Secchiello e Paletta"/>
	<Elem NameU="Bicycle" Name="Bicicletta"/>
	<Elem NameU="Building Blocks" Name="Costruzioni"/>
	<Elem NameU="Robot" Name="Robot"/>
	<Elem NameU="Kite" Name="Aquilone"/>
	<Elem NameU="Russian Doll" Name="Matrioska"/>
	<Elem NameU="Water Gun" Name="Pistola ad Acqua"/>
	<Elem NameU="Castle" Name="Castello"/>
	<Elem NameU="Excavator" Name="Scavatore"/>
	<Elem NameU="Scooter" Name="Scooter"/>
	<Elem NameU="Rocket" Name="Razzo"/>
	<Elem NameU="Ice Cream" Name="Gelato"/>
	<Elem NameU="Ribbon" Name="Fiocco"/>
	<Elem NameU="Balloon" Name="Palloncino"/>
	<Elem NameU="Chocolate" Name="Cioccolata"/>
	<Elem NameU="Crayfish" Name="Gambero"/>
	<Elem NameU="Boy" Name="Bambino"/>
	<Elem NameU="Girl" Name="Bambina"/>
	<Elem NameU="Hanbok" Name="Hanbok"/>
	<Elem NameU="Clown" Name="Clown"/>
</Lib>