<?xml version="1.0" encoding="utf-8"?><Lib nameU="Cisco Safe Threat Icons"><Elem NameU="Threat A1" Name="ボタン A1"/><Elem NameU="Threat A2" Name="ボタン A2"/><Elem NameU="Threat A3" Name="ボタン A3"/><Elem NameU="Threat A4" Name="ボタン A4"/><Elem NameU="Threat A5" Name="ボタン A5"/><Elem NameU="Threat A6" Name="ボタン A6"/><Elem NameU="Threat A7" Name="ボタン A7"/><Elem NameU="Threat A8" Name="ボタン A8"/><Elem NameU="Threat B1" Name="ボタン B1"/><Elem NameU="Threat B2" Name="ボタン B2"/><Elem NameU="Threat B3" Name="ボタン B3"/><Elem NameU="Threat B4" Name="ボタン B4"/><Elem NameU="Threat B5" Name="ボタン B5"/><Elem NameU="Threat B6" Name="ボタン B6"/><Elem NameU="Threat B7" Name="ボタン B7"/><Elem NameU="Threat B8" Name="ボタン B8"/><Elem NameU="Threat C1" Name="ボタン C1"/><Elem NameU="Threat C2" Name="ボタン C2"/><Elem NameU="Threat C3" Name="ボタン C3"/><Elem NameU="Threat C4" Name="ボタン C4"/><Elem NameU="Threat C5" Name="ボタン C5"/><Elem NameU="Threat C6" Name="ボタン C6"/><Elem NameU="Threat C7" Name="ボタン C7"/><Elem NameU="Threat C8" Name="ボタン C8"/><Elem NameU="Threat D1" Name="ボタン D1"/><Elem NameU="Threat D2" Name="ボタン D2"/><Elem NameU="Threat D3" Name="ボタン D3"/><Elem NameU="Threat D4" Name="ボタン D4"/><Elem NameU="Threat D5" Name="ボタン D5"/><Elem NameU="Threat D6" Name="ボタン D6"/><Elem NameU="Threat D7" Name="ボタン D7"/><Elem NameU="Threat D8" Name="ボタン D8"/><Elem NameU="Threat E1" Name="ボタン E1"/><Elem NameU="Threat E2" Name="ボタン E2"/><Elem NameU="Threat E3" Name="ボタン E3"/><Elem NameU="Threat E4" Name="ボタン E4"/><Elem NameU="Threat E5" Name="ボタン E5"/><Elem NameU="Threat E6" Name="ボタン E6"/><Elem NameU="Threat E7" Name="ボタン E7"/><Elem NameU="Threat E8" Name="ボタン E8"/></Lib>