<?xml version="1.0" encoding="UTF-8"?>

<Lib nameU="Daily Life Icons">

<Elem Name="トイレットペーパー" NameU="Toilet Paper"/>

<Elem Name="花瓶" NameU="Vase"/>

<Elem Name="化粧鏡" NameU="Makeup Mirror"/>

<Elem Name="電気スタンド" NameU="Table Lamp"/>

<Elem Name="腕時計" NameU="Watch"/>

<Elem Name="電球" NameU="Light Bulb"/>

<Elem Name="読書灯" NameU="Reading Lamp"/>

<Elem Name="電灯" NameU="Electric Light"/>

<Elem Name="キー" NameU="key"/>

<Elem Name="ガス" NameU="Gas"/>

<Elem Name="扇風機" NameU="Electric Fan"/>

<Elem Name="プラグ" NameU="Plug"/>

<Elem Name="ゴブレット" NameU="Goblet"/>

<Elem Name="ナイフとフォーク" NameU="Knife and Fork"/>

<Elem Name="スプーンとナイフ" NameU="Spoon and Knife"/>

<Elem Name="赤ワイングラス" NameU="Red Wine Glass"/>

<Elem Name="ビールジョッキ" NameU="Beer Mug"/>

<Elem Name="コーヒー" NameU="Coffee"/>

<Elem Name="ロック" NameU="Lock"/>

<Elem Name="お店" NameU="Store"/>

<Elem Name="薬箱" NameU="Medicine Box"/>

<Elem Name="ストローハット" NameU="Straw Hat"/>

<Elem Name="フリップ・フロップ" NameU="Flip Flop"/>

<Elem Name="エアコン" NameU="Air Conditioning"/>

<Elem Name="エアコン" NameU="Air Conditioner"/>

<Elem Name="衣類" NameU="Clothes"/>

<Elem Name="日記" NameU="Diary"/>

<Elem Name="写真" NameU="Photo"/>

<Elem Name="バスタブ" NameU="Bathtub"/>

<Elem Name="フラット" NameU="Flats"/>

<Elem Name="ブラシ" NameU="Brush"/>

<Elem Name="パレット" NameU="Palette"/>

<Elem Name="傘" NameU="Umbrella"/>

<Elem Name="バチェラーキャップ" NameU="Bachelor Cap"/>

<Elem Name="メガネ" NameU="Glasses"/>

<Elem Name="ヘッドセット" NameU="Headset"/>

<Elem Name="音楽" NameU="Music"/>

<Elem Name="ゲームリモコン" NameU="Game Remote Control"/>

<Elem Name="アイスクリーム" NameU="Ice Cream"/>

<Elem Name="携帯電話" NameU="Mobile Phone"/>

<Elem Name="鉢植え" NameU="Potted Plant"/>

<Elem Name="プレイバック" NameU="Video Playback"/>

<Elem Name="フラスコ" NameU="Flask"/>

<Elem Name="ハート" NameU="Heart"/>

<Elem Name="誕生日ケーキ" NameU="Birthday Cake"/>

<Elem Name="遠眼鏡" NameU="Telescope"/>

<Elem Name="タバコ禁止" NameU="No Smoking"/>

<Elem Name="キャンドル" NameU="Candle"/>

<Elem Name="火" NameU="Fire"/>

<Elem Name="狙い" NameU="Aims"/>

<Elem Name="ダイアローグ" NameU="Dialogue"/>

<Elem Name="ナビゲーション" NameU="Navigation"/>

<Elem Name="金槌" NameU="Hammer"/>

<Elem Name="マイク" NameU="Microphone"/>

</Lib>