<?xml version="1.0" encoding="UTF-8"?>
<Lib nameU="Gift Voucher"><Elem NameU="Gift Ribbon" Name="ギフトリボン"/><Elem NameU="Gift Ribbon 2" Name="ギフトリボン 2"/><Elem NameU="Gift Ribbon 3" Name="ギフトリボン 3"/><Elem NameU="Gift Ribbon 4" Name="ギフトリボン 4"/><Elem NameU="Gift Ribbon 5" Name="ギフトリボン 5"/><Elem NameU="Gift Ribbon 6" Name="ギフトリボン 6"/><Elem NameU="Bow" Name="弓"/><Elem NameU="Bow 2" Name="弓 2"/><Elem NameU="Price Tag" Name="値札"/><Elem NameU="Price Tag 2" Name="値札 2"/><Elem NameU="Price Tag 3" Name="値札 3"/><Elem NameU="Price Sticker" Name="価格ステッカー"/><Elem NameU="Price Sticker 2" Name="価格ステッカー 2"/><Elem NameU="Price Sticker 3" Name="価格ステッカー 3"/><Elem NameU="Price Sticker 4" Name="価格ステッカー 4"/><Elem NameU="Price Sticker 5" Name="価格ステッカー 5"/><Elem NameU="Gift" Name="ギフト"/><Elem NameU="Gift 2" Name="ギフト 2"/><Elem NameU="Thank You Tag" Name="感謝タグ"/><Elem NameU="Price Up" Name="値上がり"/><Elem NameU="Price Down" Name="値下げ"/><Elem NameU="Sale Tag" Name="販売タグ"/><Elem NameU="Sale Tag 2" Name="販売タグ 2"/><Elem NameU="Sale Banner" Name="セールのバナー"/><Elem NameU="Ribbons" Name="リボン"/><Elem NameU="Ribbons 2" Name="リボン 2"/><Elem NameU="Ribbons 3" Name="リボン 3"/></Lib>