<?xml version="1.0" encoding="UTF-8"?>
<Lib nameU="Yourdon and Coad"><Elem NameU="Class and Object" Name="クラスとオブジェクト"/><Elem NameU="Class" Name="クラス"/><Elem NameU="Object State" Name="オブジェクト状態"/><Elem NameU="Gen-spec Structure" Name="Gen-spec 構造"/><Elem NameU="Whole-part Structure" Name="Whole-part 構造"/><Elem NameU="Condition" Name="条件"/><Elem NameU="Loop" Name="ループ"/><Elem NameU="External Interactor" Name="外部相互作用"/><Elem NameU="Data Process" Name="データ処理"/><Elem NameU="Multiple Process" Name="複数の処理"/><Elem NameU="State" Name="状態"/><Elem NameU="Multiple State" Name="多重状態"/><Elem NameU="Stop State" Name="停止状態"/><Elem NameU="Stop State 2" Name="停止状態 2"/><Elem NameU="Process" Name="処理"/><Elem NameU="Center to Center" Name="センターからセンターへ"/><Elem NameU="Loop on Center" Name="ループからセンターへ"/><Elem NameU="Data Store" Name="データストア"/><Elem NameU="Connector" Name="コネクタ"/><Elem NameU="Semicircle" Name="半円"/></Lib>