<?xml version="1.0" encoding="utf-8"?>
<Lib NameU="Child Dress">
    <Elem NameU="Child dress 1" Name="어린이 복장 1"/>
    <Elem NameU="Child dress 2" Name="어린이 복장 2"/>
    <Elem NameU="Child dress 3" Name="어린이 복장 3"/>
    <Elem NameU="Child dress 4" Name="어린이 복장 4"/>
    <Elem NameU="Child dress 5" Name="어린이 복장 5"/>
    <Elem NameU="Child dress 6" Name="어린이 복장 6"/>
    <Elem NameU="Child dress 7" Name="어린이 복장 7"/>
    <Elem NameU="Child dress 8" Name="어린이 복장 8"/>
    <Elem NameU="Child dress 9" Name="어린이 복장 9"/>
    <Elem NameU="Child dress 10" Name="어린이 복장 10"/>
    <Elem NameU="Child dress 11" Name="어린이 복장 11"/>
    <Elem NameU="Child dress 12" Name="어린이 복장 12"/>
    <Elem NameU="Child dress 13" Name="어린이 복장 13"/>
    <Elem NameU="Child dress 14" Name="어린이 복장 14"/>
    <Elem NameU="Child dress 15" Name="어린이 복장 15"/>
    <Elem NameU="Child dress 16" Name="어린이 복장 16"/>
    <Elem NameU="Child dress 17" Name="어린이 복장 17"/>
    <Elem NameU="Child dress 18" Name="어린이 복장 18"/>
    <Elem NameU="Child dress 19" Name="어린이 복장 19"/>
    <Elem NameU="Child dress 20" Name="어린이 복장 20"/>
    <Elem NameU="Child dress 21" Name="어린이 복장 21"/>
    <Elem NameU="Child dress 22" Name="어린이 복장 22"/>
    <Elem NameU="Child dress 23" Name="어린이 복장 23"/>
    <Elem NameU="Child dress 24" Name="어린이 복장 24"/>
    <Elem NameU="Child dress 25" Name="어린이 복장 25"/>
    <Elem NameU="Child dress 26" Name="어린이 복장 26"/>
    <Elem NameU="Child dress 27" Name="어린이 복장 27"/>
    <Elem NameU="Child dress 28" Name="어린이 복장 28"/>
    <Elem NameU="Child dress 29" Name="어린이 복장 29"/>
    <Elem NameU="Child dress 30" Name="어린이 복장 30"/>
</Lib>
